scifit/__init__.py
scifit/errors/__init__.py
scifit/errors/base.py
scifit/interfaces/__init__.py
scifit/interfaces/kinetics.py
scifit/interfaces/mixins.py
scifit/interfaces/solvers.py
scifit/solvers/__init__.py
scifit/solvers/chromatography.py
scifit/solvers/illdefined.py
scifit/solvers/kinetics.py
scifit/solvers/linear.py
scifit/solvers/scientific.py
scifit/solvers/specials.py
scifit/tests/__init__.py
scifit/tests/helpers.py
scifit/tests/test_fixed_issues.py
scifit/tests/test_interfaces.py
scifit/tests/test_kinetics.py
scifit/tests/test_solvers_book.py
scifit/tests/test_solvers_chromatography.py
scifit/tests/test_solvers_illdefined.py
scifit/tests/test_solvers_kinetics.py
scifit/tests/test_solvers_linear.py
scifit/tests/test_solvers_report.py
scifit/tests/test_solvers_scientific.py
scifit/tests/test_solvers_specials.py
scifit/toolbox/__init__.py
scifit/toolbox/report.py
scifit-0.1.15.dist-info/AUTHORS
scifit-0.1.15.dist-info/LICENSE
scifit-0.1.15.dist-info/LICENSE_bundled
scifit-0.1.15.dist-info/METADATA
scifit-0.1.15.dist-info/WHEEL
scifit-0.1.15.dist-info/top_level.txt
scifit-0.1.15.dist-info/RECORD
