Metadata-Version: 2.1
Name: scifit
Version: 0.1.15
Summary: Scientific Fit for Python
Author-email: Jean Landercy <jeanlandercy@live.com>
License: BSD 3-Clause License
Project-URL: Homepage, https://github.com/jlandercy/scifit
Keywords: scientific,curve-fitting,optimization
Classifier: Intended Audience :: Science/Research
Classifier: Intended Audience :: Education
Classifier: Topic :: Education
Classifier: Topic :: Scientific/Engineering
Classifier: Topic :: Scientific/Engineering :: Mathematics
Classifier: Topic :: Scientific/Engineering :: Chemistry
Classifier: Topic :: Utilities
Classifier: License :: OSI Approved :: BSD License
Classifier: Natural Language :: English
Classifier: Operating System :: OS Independent
Classifier: Programming Language :: Python :: 3.9
Classifier: Programming Language :: Python :: 3.10
Classifier: Programming Language :: Python :: 3.11
Requires-Python: >=3.9
License-File: LICENSE
License-File: LICENSE_bundled
License-File: AUTHORS
Requires-Dist: matplotlib (>=3.7.2)
Requires-Dist: numpy (>=1.25.2)
Requires-Dist: numdifftools (>=0.9.41)
Requires-Dist: pandas (>=2.0.3)
Requires-Dist: scikit-learn (>=1.3.0)
Requires-Dist: scipy (>=1.11.1)
Requires-Dist: pybaselines (>=1.0.0)
Requires-Dist: Jinja2 (==3.1.2)
Requires-Dist: pypandoc (>=1.11)
Requires-Dist: tabulate (==0.9.0)
Provides-Extra: dev
Requires-Dist: alabaster (>=0.7.12) ; extra == 'dev'
Requires-Dist: anybadge (>=1.7.0) ; extra == 'dev'
Requires-Dist: appdirs (>=1.4.4) ; extra == 'dev'
Requires-Dist: argcomplete (>=1.12.2) ; extra == 'dev'
Requires-Dist: astroid (>=2.4.2) ; extra == 'dev'
Requires-Dist: async-generator (>=1.10) ; extra == 'dev'
Requires-Dist: attrs (>=20.3.0) ; extra == 'dev'
Requires-Dist: bumpver (>=2023.1126) ; extra == 'dev'
Requires-Dist: Babel (>=2.9.0) ; extra == 'dev'
Requires-Dist: backcall (>=0.2.0) ; extra == 'dev'
Requires-Dist: bandit (>=1.7.0) ; extra == 'dev'
Requires-Dist: beautifulsoup4 (>=4.9.3) ; extra == 'dev'
Requires-Dist: black (>=20.8b1) ; extra == 'dev'
Requires-Dist: bleach (>=3.2.1) ; extra == 'dev'
Requires-Dist: certifi (>=2020.12.5) ; extra == 'dev'
Requires-Dist: chardet (>=4.0.0) ; extra == 'dev'
Requires-Dist: click (>=7.1.2) ; extra == 'dev'
Requires-Dist: colorama (>=0.4.4) ; extra == 'dev'
Requires-Dist: colorlog (>=4.6.2) ; extra == 'dev'
Requires-Dist: commonmark (>=0.9.1) ; extra == 'dev'
Requires-Dist: coverage (>=5.3.1) ; extra == 'dev'
Requires-Dist: decorator (>=4.4.2) ; extra == 'dev'
Requires-Dist: defusedxml (>=0.6.0) ; extra == 'dev'
Requires-Dist: distlib (>=0.3.1) ; extra == 'dev'
Requires-Dist: docutils (>=0.16) ; extra == 'dev'
Requires-Dist: dparse (>=0.5.1) ; extra == 'dev'
Requires-Dist: entrypoints (>=0.3) ; extra == 'dev'
Requires-Dist: filelock (>=3.0.12) ; extra == 'dev'
Requires-Dist: flake8 (>=3.8.4) ; extra == 'dev'
Requires-Dist: flake8-junit-report (>=2.1.0) ; extra == 'dev'
Requires-Dist: furo (>=2020.12.30b24) ; extra == 'dev'
Requires-Dist: gitdb (>=4.0.5) ; extra == 'dev'
Requires-Dist: GitPython (>=3.1.11) ; extra == 'dev'
Requires-Dist: idna (>=2.10) ; extra == 'dev'
Requires-Dist: imagesize (>=1.2.0) ; extra == 'dev'
Requires-Dist: importlib-metadata (>=3.3.0) ; extra == 'dev'
Requires-Dist: ipykernel (>=5.4.2) ; extra == 'dev'
Requires-Dist: ipython (>=7.19.0) ; extra == 'dev'
Requires-Dist: ipython-genutils (>=0.2.0) ; extra == 'dev'
Requires-Dist: isort (>=5.7.0) ; extra == 'dev'
Requires-Dist: jedi (>=0.18.0) ; extra == 'dev'
Requires-Dist: Jinja2 (>=2.11.2) ; extra == 'dev'
Requires-Dist: joblib (>=1.0.0) ; extra == 'dev'
Requires-Dist: jsonschema (>=3.2.0) ; extra == 'dev'
Requires-Dist: jupyter-client (>=6.1.7) ; extra == 'dev'
Requires-Dist: jupyter-core (>=4.7.0) ; extra == 'dev'
Requires-Dist: jupyterlab-pygments (>=0.1.2) ; extra == 'dev'
Requires-Dist: lazy-object-proxy (>=1.4.3) ; extra == 'dev'
Requires-Dist: lxml (>=4.6.2) ; extra == 'dev'
Requires-Dist: m2r2 (>=0.2.7) ; extra == 'dev'
Requires-Dist: MarkupSafe (>=1.1.1) ; extra == 'dev'
Requires-Dist: mccabe (>=0.6.1) ; extra == 'dev'
Requires-Dist: mistune (>=0.8.4) ; extra == 'dev'
Requires-Dist: mypy (>=0.790) ; extra == 'dev'
Requires-Dist: mypy-extensions (>=0.4.3) ; extra == 'dev'
Requires-Dist: nbclient (>=0.5.1) ; extra == 'dev'
Requires-Dist: nbconvert (>=6.0.7) ; extra == 'dev'
Requires-Dist: nbformat (>=5.0.8) ; extra == 'dev'
Requires-Dist: nbsphinx (>=0.8.0) ; extra == 'dev'
Requires-Dist: nest-asyncio (>=1.4.3) ; extra == 'dev'
Requires-Dist: nox (>=2020.12.31) ; extra == 'dev'
Requires-Dist: numpy (>=1.19.4) ; extra == 'dev'
Requires-Dist: packaging (>=20.8) ; extra == 'dev'
Requires-Dist: pandas (>=1.2.0) ; extra == 'dev'
Requires-Dist: pandocfilters (>=1.4.3) ; extra == 'dev'
Requires-Dist: parso (>=0.8.1) ; extra == 'dev'
Requires-Dist: pathspec (>=0.8.1) ; extra == 'dev'
Requires-Dist: pbr (>=5.5.1) ; extra == 'dev'
Requires-Dist: pickleshare (>=0.7.5) ; extra == 'dev'
Requires-Dist: pluggy (>=0.13.1) ; extra == 'dev'
Requires-Dist: prompt-toolkit (>=3.0.8) ; extra == 'dev'
Requires-Dist: py (>=1.10.0) ; extra == 'dev'
Requires-Dist: pycodestyle (>=2.6.0) ; extra == 'dev'
Requires-Dist: pyflakes (>=2.2.0) ; extra == 'dev'
Requires-Dist: Pygments (>=2.7.3) ; extra == 'dev'
Requires-Dist: pylint (>=2.6.0) ; extra == 'dev'
Requires-Dist: pypandoc (>=1.11) ; extra == 'dev'
Requires-Dist: pyparsing (>=2.4.7) ; extra == 'dev'
Requires-Dist: pyproj (>=3.0.0.post1) ; extra == 'dev'
Requires-Dist: pyrsistent (>=0.17.3) ; extra == 'dev'
Requires-Dist: python-dateutil (>=2.8.1) ; extra == 'dev'
Requires-Dist: pytz (>=2020.5) ; extra == 'dev'
Requires-Dist: PyYAML (>=5.3.1) ; extra == 'dev'
Requires-Dist: pyzmq (>=20.0.0) ; extra == 'dev'
Requires-Dist: recommonmark (>=0.7.1) ; extra == 'dev'
Requires-Dist: regex (>=2020.11.13) ; extra == 'dev'
Requires-Dist: requests (>=2.25.1) ; extra == 'dev'
Requires-Dist: safety (>=1.10.1) ; extra == 'dev'
Requires-Dist: scikit-learn (>=0.24.0) ; extra == 'dev'
Requires-Dist: scipy (>=1.6.0) ; extra == 'dev'
Requires-Dist: six (>=1.15.0) ; extra == 'dev'
Requires-Dist: smmap (>=3.0.4) ; extra == 'dev'
Requires-Dist: snowballstemmer (>=2.0.0) ; extra == 'dev'
Requires-Dist: soupsieve (>=2.1) ; extra == 'dev'
Requires-Dist: Sphinx (>=3.4.1) ; extra == 'dev'
Requires-Dist: sphinxcontrib-applehelp (>=1.0.2) ; extra == 'dev'
Requires-Dist: sphinxcontrib-devhelp (>=1.0.2) ; extra == 'dev'
Requires-Dist: sphinxcontrib-htmlhelp (>=1.0.3) ; extra == 'dev'
Requires-Dist: sphinxcontrib-jsmath (>=1.0.1) ; extra == 'dev'
Requires-Dist: sphinxcontrib-qthelp (>=1.0.3) ; extra == 'dev'
Requires-Dist: sphinxcontrib-serializinghtml (>=1.1.4) ; extra == 'dev'
Requires-Dist: stevedore (>=3.3.0) ; extra == 'dev'
Requires-Dist: testpath (>=0.4.4) ; extra == 'dev'
Requires-Dist: threadpoolctl (>=2.1.0) ; extra == 'dev'
Requires-Dist: toml (>=0.10.2) ; extra == 'dev'
Requires-Dist: tornado (>=6.1) ; extra == 'dev'
Requires-Dist: tox (>=3.20.1) ; extra == 'dev'
Requires-Dist: traitlets (>=5.0.5) ; extra == 'dev'
Requires-Dist: typed-ast (>=1.4.2) ; extra == 'dev'
Requires-Dist: typing-extensions (>=3.7.4.3) ; extra == 'dev'
Requires-Dist: unittest-xml-reporting (>=3.0.4) ; extra == 'dev'
Requires-Dist: urllib3 (>=1.26.2) ; extra == 'dev'
Requires-Dist: virtualenv (>=20.2.2) ; extra == 'dev'
Requires-Dist: wcwidth (>=0.2.5) ; extra == 'dev'
Requires-Dist: webencodings (>=0.5.1) ; extra == 'dev'
Requires-Dist: wrapt (>=1.12.1) ; extra == 'dev'
Requires-Dist: zipp (>=3.4.0) ; extra == 'dev'
